CHANGES.rst
LICENSE.txt
MANIFEST.in
README.rst
run_tests.sh
setup.py
examples/demo.py
examples/export.py
examples/soql2atom.py
src/beatbox/__init__.py
src/beatbox/_beatbox.py
src/beatbox/marshall.py
src/beatbox/python_client.py
src/beatbox/xmltramp.py
src/beatbox.egg-info/PKG-INFO
src/beatbox.egg-info/SOURCES.txt
src/beatbox.egg-info/dependency_links.txt
src/beatbox.egg-info/top_level.txt
src/beatbox/tests/test_beatbox.py
src/beatbox/tests/test_benchmark.py
src/beatbox/tests/test_pythonClient.py