Metadata-Version: 1.1
Name: beatbox
Version: 32.0
Summary: A Python library for querying/updating Saleforce.com data via SOAP API
Home-page: http://code.google.com/p/salesforce-beatbox/
Author: Simon Fell et al
Author-email: plonesf@googlegroups.com
License: GNU GENERAL PUBLIC LICENSE Version 2
Keywords: python salesforce salesforce.com
Platform: UNKNOWN
Classifier: Development Status :: 5 - Production/Stable
